NovitecCameraAPIWinPy/NovitecCameraAPIWinPy.py
NovitecCameraAPIWinPy/__init__.py
NovitecCameraAPIWinPy/_internal/NOVITECCAMERAAPIC.dll
NovitecCameraAPIWinPy/_internal/NovitecCameraAPI.dll
NovitecCameraAPIWinPy/_internal/libcrypto-1_1-x64.dll
NovitecCameraAPIWinPy/_internal/libcurl.dll
NovitecCameraAPIWinPy/_internal/libssl-1_1-x64.dll
NovitecCameraAPIWinPy-0.0.6.dist-info/METADATA
NovitecCameraAPIWinPy-0.0.6.dist-info/WHEEL
NovitecCameraAPIWinPy-0.0.6.dist-info/top_level.txt
NovitecCameraAPIWinPy-0.0.6.dist-info/RECORD
