Metadata-Version: 2.1
Name: NovitecCameraAPIWinPy
Version: 0.0.6
Summary: Python wrapper for Novitec Camera API (Windows only)
Author: kkomadev
Author-email: kkomadev@gmail.com
Classifier: Programming Language :: Python :: 3
Classifier: License :: OSI Approved :: MIT License
Classifier: Operating System :: Microsoft :: Windows
Classifier: Development Status :: 2 - Pre-Alpha
Classifier: Topic :: Software Development :: Libraries :: Python Modules
Requires-Python: >=3.10.11
